ftools/__init__.py
ftools/callable.py
ftools/collection.py
ftools/iterable.py
ftools/mapping.py
ftools/optional.py
ftools/sequence.py
ftools-0.2.10.dist-info/WHEEL
ftools-0.2.10.dist-info/METADATA
ftools-0.2.10.dist-info/RECORD
