Metadata-Version: 2.1
Name: ftools
Version: 0.2.10
Summary: Functional programming utilities
License: MIT
Author: Iddan Aaronsohn
Author-email: mail@aniddan.com
Requires-Python: >=3.6,<4.0
Classifier: License :: OSI Approved :: MIT License
Classifier: Programming Language :: Python :: 3
Classifier: Programming Language :: Python :: 3.6
Classifier: Programming Language :: Python :: 3.7
Classifier: Programming Language :: Python :: 3.8
Requires-Dist: cardinality (>=0.1.1,<0.2.0)
Requires-Dist: mypy_extensions (>=0.4.3,<0.5.0)
